function_error_handling.py
function_error_handling/__init__.py
function_error_handling/function_error_handling.py
function_error_handling/validators.py
trython/__init__.py
trython/trython.py
trython/validators.py
function_error_handling-3.0.2.dist-info/LICENSE
function_error_handling-3.0.2.dist-info/METADATA
function_error_handling-3.0.2.dist-info/WHEEL
function_error_handling-3.0.2.dist-info/top_level.txt
function_error_handling-3.0.2.dist-info/RECORD
